merge_code/__init__.py
merge_code/main.py
merge_code-0.2.4.dist-info/METADATA
merge_code-0.2.4.dist-info/WHEEL
merge_code-0.2.4.dist-info/entry_points.txt
merge_code-0.2.4.dist-info/licenses/LICENSE
merge_code-0.2.4.dist-info/RECORD
