Metadata-Version: 2.3
Name: merge_code
Version: 0.2.4
Summary: A tool to merge source code files for software copyright application
Project-URL: Homepage, https://github.com/songyi1999/merge_code
Project-URL: Bug Tracker, https://github.com/songyi1999/merge_code/issues
Author-email: sy <songyi1999@gmail.com>
License-File: LICENSE
Classifier: License :: OSI Approved :: MIT License
Classifier: Operating System :: OS Independent
Classifier: Programming Language :: Python :: 3
Requires-Python: >=3.6
